recollapse/__init__.py
recollapse/__main__.py
recollapse/_version.py
recollapse/cli.py
recollapse/core.py
recollapse-1.0.0.dist-info/licenses/LICENSE
recollapse-1.0.0.dist-info/METADATA
recollapse-1.0.0.dist-info/WHEEL
recollapse-1.0.0.dist-info/entry_points.txt
recollapse-1.0.0.dist-info/top_level.txt
recollapse-1.0.0.dist-info/RECORD
