Metadata-Version: 2.4
Name: recollapse
Version: 1.0.0
Summary: REcollapse is a helper tool for black-box regex fuzzing to bypass validations and discover normalizations in web applications
Home-page: https://github.com/0xacb/recollapse
Author: 0xacb
Author-email: 
License: MIT
Project-URL: Bug Reports, https://github.com/0xacb/recollapse/issues
Project-URL: Source, https://github.com/0xacb/recollapse
Project-URL: Documentation, https://github.com/0xacb/recollapse#readme
Keywords: security,fuzzing,regex,bypass,normalization,waf
Classifier: Programming Language :: Python :: 3
Classifier: Operating System :: OS Independent
Classifier: Intended Audience :: Developers
Classifier: Topic :: Security
Classifier: Topic :: Software Development :: Testing
Requires-Python: >=3.7
License-File: LICENSE
Requires-Dist: unidecode
Requires-Dist: prettytable
Dynamic: author
Dynamic: classifier
Dynamic: description
Dynamic: description-content-type
Dynamic: home-page
Dynamic: keywords
Dynamic: license
Dynamic: license-file
Dynamic: project-url
Dynamic: requires-dist
Dynamic: requires-python
Dynamic: summary
